README.md
setup.py
bin/pkcrypt
bin/pkdcrypt
bin/pkecrypt
pkcrypt/__init__.py
pkcrypt/__main__.py
pkcrypt/api.py
pkcrypt/cli.py
pkcrypt/crypt.py
pkcrypt/test.py
pkcrypt.egg-info/PKG-INFO
pkcrypt.egg-info/SOURCES.txt
pkcrypt.egg-info/dependency_links.txt
pkcrypt.egg-info/pbr.json
pkcrypt.egg-info/requires.txt
pkcrypt.egg-info/top_level.txt