Metadata-Version: 1.0
Name: pkcrypt
Version: 1.1.0
Summary: public key cryptography
Home-page: https://github.com/val-labs/pkcrypt/tree/master/pkcrypt
Author: Joel Ward
Author-email: jmward@gmail.com
License: MIT
Platform: any
